[
{
  "word": "צוואר",
  "representative_group": [
    "צוואר",
    "הצוואר",
    "לצוואר",
    "בצוואר",
    "מצוואר",
    "מהצוואר",
    "ולצוואר",
    "צווארי",
    "צווארך",
    "צוואריו",
    "צוואריה",
    "צווארם",
    "צווארן",
    "צווארים",
    "צווארות",
    "צואר",
    "הצואר",
    "צוארים",
    "לעורף",
    "עורף",
    "העורף",
    "עורפו",
    "בעורף",
    "throat",
    "throats",
    "neck",
    "neck",
    "necks",
    "cervical",
    "cervix"
  ]
},
{
  "word": "ברך",
  "representative_group": [
    "ברך",
    "הברך",
    "בברך",
    "לברך",
    "מהברך",
    "מברך",
    "וברך",
    "ברכי",
    "ברכך",
    "ברכו",
    "ברכה",
    "ברכיה",
    "ברכם",
    "ברכן",
    "ברכיים",
    "הברכיים",
    "לברכיים",
    "בברכיים",
    "ברכים",
    "ברכ",
    "kneecap",
    "knee",
    "knees",
    "patella",
    "genicular"
  ]
},
{
  "word": "גב",
  "representative_group": [
    "גב",
    "הגב",
    "לגב",
    "בגב",
    "מהגב",
    "מגב",
    "וגב",
    "גבי",
    "גבך",
    "גבו",
    "גבה",
    "גביהם",
    "גבן",
    "גבים",
    "גו",
    "שכם",
    "back",
    "backs",
    "back",
    "spine",
    "dorsal",
    "vertebral"
  ]
},
{
  "word": "קרסול",
  "representative_group": [
    "קרסול",
    "הקרסול",
    "לקרסול",
    "בקרסול",
    "מהקרסול",
    "מקרסול",
    "וקרסול",
    "קרסולי",
    "קרסולך",
    "קרסולו",
    "קרסולה",
    "קרסוליהם",
    "קרסולן",
    "קרסולים",
    "קרסוליים",
    "קרסולין",
    "ankle",
    "ankles",
    "malleolus",
    "tarsus"
  ]
},
{
  "word": "כתף",
  "representative_group": [
    "כתף",
    "הכתף",
    "לכתף",
    "בכתף",
    "מכתף",
    "מהכתף",
    "וכתף",
    "כתפי",
    "כתפך",
    "כתפו",
    "כתפה",
    "כתפם",
    "כתפן",
    "כתפיים",
    "הכתפיים",
    "לכתפיים",
    "בכתפיים",
    "על הכתפיים",
    "כתפים",
    "שכם",
    "shoulder",
    "shoulders",
    "deltoid",
    "rotator cuff",
    "glenohumeral",
    "acromion",
    "scapula",
    "clavicle"
  ]
},
{
  "word": "מרפק",
  "representative_group": [
    "מרפק",
    "המרפק",
    "למרפק",
    "במרפק",
    "ממרפק",
    "מהמרפק",
    "ומרפק",
    "מרפקי",
    "מרפקך",
    "מרפקו",
    "מרפקה",
    "מרפקיהם",
    "מרפקן",
    "מרפקים",
    "המרפקים",
    "למרפקים",
    "במרפקים",
    "מרפקיים",
    "elbow",
    "elbows",
    "olecranon",
    "ulna",
    "humerus",
    "radial head",
    "cubital",
    "antecubital"
  ]
},
{
  "word": "לסת",
  "representative_group": [
    "לסת",
    "הלסת",
    "ללסת",
    "בלסת",
    "מלסת",
    "מהלסת",
    "ולסת",
    "לסתי",
    "לסתך",
    "לסתו",
    "לסתה",
    "לסתם",
    "לסתן",
    "לסתות",
    "הלסתות",
    "בלסתות",
    "לסט",
    "jaw",
    "jaws",
    "jawbone",
    "mandible",
    "maxilla",
    "temporomandibular",
    "TMJ"
  ]
}
]